investec_python-1.1.0.dist-info/METADATA
investec_python-1.1.0.dist-info/WHEEL
investec_python-1.1.0.dist-info/entry_points.txt
investec_python-1.1.0.dist-info/licenses/LICENSE
investec_python/__init__.py
investec_python/api/__init__.py
investec_python/api/api.py
investec_python/api/v1/__init__.py
investec_python/api/v1/accounts.py
investec_python/auth.py
investec_python/client.py
investec_python/exception.py
investec_python-1.1.0.dist-info/RECORD
