Metadata-Version: 2.1
Name: investec-python
Version: 1.1.0
Summary: A Python wrapper for the Investec Banking API
Author-Email: Rameez Khan <rameez@rameezkhan.dev>
License: MIT
Requires-Python: >=3.11
Requires-Dist: requests>=2.31.0
Requires-Dist: pydantic>=2.4.2
